akantu/py11_akantu.cpython-37m-x86_64-linux-gnu.so
akantu/__init__.py
akantu.libs/libakantu-a2b19b2c.so.5.0.7
akantu.libs/libiohelper-18d9bb61.so
akantu-5.0.7.post1.dist-info/COPYING
akantu-5.0.7.post1.dist-info/COPYING.lesser
akantu-5.0.7.post1.dist-info/WHEEL
akantu-5.0.7.post1.dist-info/RECORD
akantu-5.0.7.post1.dist-info/top_level.txt
akantu-5.0.7.post1.dist-info/METADATA
